[{"fullName":"Whispering Creek","universityName":"Emerald Academy"},{"fullName":"Silent Echo","universityName":"Quantum Institute"},{"fullName":"Dancing Shadow","universityName":"Celestial College"},{"fullName":"Crimson Bloom","universityName":"Mystic University"},{"fullName":"Golden Whisper","universityName":"Starlight Campus"},{"fullName":"Azure Dream","universityName":"Fusion Learning"},{"fullName":"Stone Glade","universityName":"Evergreen Studies"},{"fullName":"Silver Branch","universityName":"Pinnacle Minds"},{"fullName":"Fading Ember","universityName":"Horizon Center"},{"fullName":"Mystic Grove","universityName":"Zenith Hub"},{"fullName":"Shifting Sands","universityName":"Vortex School"},{"fullName":"Ancient Rune","universityName":"Orion University"},{"fullName":"Woven Cloud","universityName":"Nexus College"},{"fullName":"Iron Peak","universityName":"Sapphire Institute"},{"fullName":"Flowing Mist","universityName":"Terra Academia"},{"fullName":"Forgotten Song","universityName":"Echo Chambers"},{"fullName":"Bright Lumen","universityName":"Innovate College"},{"fullName":"Dark Canopy","universityName":"Shadowbrook University"},{"fullName":"Wild Fern","universityName":"Riverside Learning"},{"fullName":"Distant Comet","universityName":"Cosmic Studies"},{"fullName":"Frozen Aurora","universityName":"Arctic Hall"},{"fullName":"Silent Bell","universityName":"Chime University"},{"fullName":"Glimmering Pond","universityName":"Aqua College"},{"fullName":"Lost Key","universityName":"Enigma Institute"},{"fullName":"Vivid Hue","universityName":"Spectrum University"},{"fullName":"Soft Rain","universityName":"Gentle School"},{"fullName":"Azure Bolt","universityName":"Thunderhead Academy"},{"fullName":"Dusty Scroll","universityName":"Ancient Forum"},{"fullName":"Quiet Spark","universityName":"Luminous College"},{"fullName":"Wandering Star","universityName":"Nebula University"},{"fullName":"Green Thorn","universityName":"Briar Institute"},{"fullName":"Crystal Spire","universityName":"Quartz Academy"},{"fullName":"Echoing Cave","universityName":"Subterranean University"},{"fullName":"Sunken Ship","universityName":"Oceanic College"},{"fullName":"Rising Tide","universityName":"Current Institute"},{"fullName":"Desert Bloom","universityName":"Oasis Academy"},{"fullName":"Thunder Roar","universityName":"Stormfront University"},{"fullName":"Gentle Breeze","universityName":"Whisperwind College"},{"fullName":"Molten Core","universityName":"Volcano Institute"},{"fullName":"Sky Dancer","universityName":"Aero Academy"},{"fullName":"Deep Roots","universityName":"Earthbound University"},{"fullName":"Forest Whisper","universityName":"Sylvan College"},{"fullName":"Cloud Weaver","universityName":"Cirrus Institute"},{"fullName":"Night Bloom","universityName":"Nocturne Academy"},{"fullName":"River Stone","universityName":"Cascade University"},{"fullName":"Winter Frost","universityName":"Glacial College"},{"fullName":"Spring Dew","universityName":"Vernal Institute"},{"fullName":"Autumn Leaf","universityName":"Fallen Academy"},{"fullName":"Summer Haze","universityName":"Solstice University"},{"fullName":"Burning Coal","universityName":"Cinder College"},{"fullName":"Silver Coin","universityName":"Treasure Institute"},{"fullName":"Lost Valley","universityName":"Hidden Academy"},{"fullName":"Silent Knight","universityName":"Valor University"},{"fullName":"Golden Shield","universityName":"Bastion College"},{"fullName":"Crimson Blade","universityName":"Edge Institute"},{"fullName":"Azure Sky","universityName":"Celestial Academy"},{"fullName":"Black Raven","universityName":"Onyx University"},{"fullName":"White Dove","universityName":"Purity College"},{"fullName":"Green Serpent","universityName":"Viper Institute"},{"fullName":"Red Dragon","universityName":"Inferno Academy"},{"fullName":"Blue Whale","universityName":"Abyss University"},{"fullName":"Yellow Sun","universityName":"Radiant College"},{"fullName":"Purple Moon","universityName":"Lunar Institute"},{"fullName":"Brown Bear","universityName":"Grizzly Academy"},{"fullName":"Gray Wolf","universityName":"Timber University"},{"fullName":"Orange Fox","universityName":"Russet College"},{"fullName":"Pink Flamingo","universityName":"Coral Institute"},{"fullName":"Teal Wave","universityName":"Lagoon Academy"},{"fullName":"Lime Scent","universityName":"Citrus University"},{"fullName":"Maroon Gem","universityName":"Ruby College"},{"fullName":"Indigo Night","universityName":"Twilight Institute"},{"fullName":"Violet Haze","universityName":"Lavender Academy"},{"fullName":"Bronze Statue","universityName":"Monument University"},{"fullName":"Copper Kettle","universityName":"Forge College"},{"fullName":"Steel Beam","universityName":"Structure Institute"},{"fullName":"Tin Soldier","universityName":"Regiment Academy"},{"fullName":"Zinc Oxide","universityName":"Chemical University"},{"fullName":"Platinum Ring","universityName":"Jewel College"},{"fullName":"Diamond Dust","universityName":"Sparkle Institute"},{"fullName":"Pearl Drop","universityName":"Oyster Academy"},{"fullName":"Opal Fire","universityName":"Prism University"},{"fullName":"Ruby Gleam","universityName":"Crimson College"},{"fullName":"Emerald Green","universityName":"Jade Institute"},{"fullName":"Sapphire Blue","universityName":"Azure Academy"},{"fullName":"Topaz Shine","universityName":"Golden University"},{"fullName":"Amethyst Violet","universityName":"Purple College"},{"fullName":"Garnet Red","universityName":"Deep Institute"},{"fullName":"Peridot Glow","universityName":"Olive Academy"},{"fullName":"Aquamarine Cool","universityName":"Seafoam University"},{"fullName":"Citrine Bright","universityName":"Sunshine College"},{"fullName":"Turquoise Calm","universityName":"Desert Institute"},{"fullName":"Moonstone White","universityName":"Lunar Academy"},{"fullName":"Bloodstone Dark","universityName":"Shadow University"},{"fullName":"Sunstone Warm","universityName":"Radiant College"},{"fullName":"Obsidian Mirror","universityName":"Volcanic Institute"},{"fullName":"Jasper Earth","universityName":"Terra Academy"},{"fullName":"Agate Swirl","universityName":"Vortex University"},{"fullName":"Onyx Shadow","universityName":"Nightfall College"},{"fullName":"Lapis Azure","universityName":"Deepblue Institute"},{"fullName":"Malachite Stripe","universityName":"Forest Academy"},{"fullName":"Tiger Eye Gaze","universityName":"Stare University"},{"fullName":"Falcon Wing","universityName":"Aerodynamic College"},{"fullName":"Serpent Scale","universityName":"Reptile Institute"},{"fullName":"Dragon Breath","universityName":"Blaze Academy"},{"fullName":"Phoenix Ash","universityName":"Rebirth University"},{"fullName":"asdasdasdas","universityName":"asdasdadasdd"}]